autoMKL/__init__.py
autoMKL/autoMKL.py
autoMKL-0.0.1.dist-info/LICENSE
autoMKL-0.0.1.dist-info/METADATA
autoMKL-0.0.1.dist-info/WHEEL
autoMKL-0.0.1.dist-info/top_level.txt
autoMKL-0.0.1.dist-info/RECORD
