Metadata-Version: 2.1
Name: autoMKL
Version: 0.0.1
Summary: auto kernel selection and fusion
Home-page: https://github.com/raamana/autoMKL
Author: Pradeep Reddy Raamana
Author-email: raamana@gmail.com
License: Apache Software License 2.0
Keywords: autoMKL
Platform: UNKNOWN
Classifier: Development Status :: 2 - Pre-Alpha
Classifier: Intended Audience :: Developers
Classifier: License :: OSI Approved :: Apache Software License
Classifier: Natural Language :: English
Classifier: Programming Language :: Python :: 2
Classifier: Programming Language :: Python :: 2.7
Classifier: Programming Language :: Python :: 3
Classifier: Programming Language :: Python :: 3.4
Classifier: Programming Language :: Python :: 3.5
Classifier: Programming Language :: Python :: 3.6
Classifier: Programming Language :: Python :: 3.7
